MANIFEST.in
setup.cfg
setup.py
amqpctl/__init__.py
amqpctl/command.py
amqpctl.egg-info/PKG-INFO
amqpctl.egg-info/SOURCES.txt
amqpctl.egg-info/dependency_links.txt
amqpctl.egg-info/entry_points.txt
amqpctl.egg-info/not-zip-safe
amqpctl.egg-info/requires.txt
amqpctl.egg-info/top_level.txt
docs/Makefile
docs/implementation.rst
docs/index.rst
docs/installation.rst
docs/make.bat
docs/usage.rst