Metadata-Version: 1.0
Name: amqpctl
Version: 0.2
Summary: AMQP Control Command Line Utility
Home-page: http://packages.python.org/amqpctl
Author: William Waites
Author-email: ww@styx.org
License: GPL
Keywords: amqp
Platform: UNKNOWN
